{
  "db_name": "PostgreSQL",
  "query": "SELECT \n              * \n            FROM songs",
  "describe": {
    "columns": [
      {
        "ordinal": 0,
        "name": "id",
        "type_info": "Int4"
      },
      {
        "ordinal": 1,
        "name": "title",
        "type_info": "Varchar"
      },
      {
        "ordinal": 2,
        "name": "artist",
        "type_info": "Varchar"
      },
      {
        "ordinal": 3,
        "name": "last_played_at",
        "type_info": "Date"
      },
      {
        "ordinal": 4,
        "name": "audio_file_path",
        "type_info": "Varchar"
      },
      {
        "ordinal": 5,
        "name": "created_at",
        "type_info": "Timestamp"
      }
    ],
    "parameters": {
      "Left": []
    },
    "nullable": [
      false,
      false,
      false,
      true,
      false,
      false
    ]
  },
  "hash": "e069d7c4ece7e3369541a0ccb7feb5b7b86a088d8819d96cbf31c4c0262a0b27"
}
